stackql_deploy/__init__.py
stackql_deploy/cli.py
stackql_deploy/cmd/__init__.py
stackql_deploy/cmd/base.py
stackql_deploy/cmd/build.py
stackql_deploy/cmd/teardown.py
stackql_deploy/cmd/test.py
stackql_deploy/inc/contributors.csv
stackql_deploy/lib/__init__.py
stackql_deploy/lib/bootstrap.py
stackql_deploy/lib/config.py
stackql_deploy/lib/filters.py
stackql_deploy/lib/templating.py
stackql_deploy/lib/utils.py
stackql_deploy/templates/aws/README.md.template
stackql_deploy/templates/aws/stackql_manifest.yml.template
stackql_deploy/templates/aws/resources/example_vpc.iql.template
stackql_deploy/templates/azure/README.md.template
stackql_deploy/templates/azure/stackql_manifest.yml.template
stackql_deploy/templates/azure/resources/example_res_grp.iql.template
stackql_deploy/templates/google/README.md.template
stackql_deploy/templates/google/stackql_manifest.yml.template
stackql_deploy/templates/google/resources/example_vpc.iql.template
stackql_deploy-1.9.4.data/data/share/stackql-deploy/completions/stackql-deploy-completion.bash
stackql_deploy-1.9.4.data/data/share/stackql-deploy/completions/stackql-deploy-completion.fish
stackql_deploy-1.9.4.data/data/share/stackql-deploy/completions/stackql-deploy-completion.ps1
stackql_deploy-1.9.4.data/data/share/stackql-deploy/completions/stackql-deploy-completion.zsh
stackql_deploy-1.9.4.dist-info/licenses/LICENSE
stackql_deploy-1.9.4.dist-info/METADATA
stackql_deploy-1.9.4.dist-info/WHEEL
stackql_deploy-1.9.4.dist-info/entry_points.txt
stackql_deploy-1.9.4.dist-info/top_level.txt
stackql_deploy-1.9.4.dist-info/RECORD
