Metadata-Version: 2.4
Name: stackql-deploy
Version: 1.9.4
Summary: Model driven resource provisioning and deployment framework using StackQL.
Home-page: https://github.com/stackql/stackql-deploy
Author: Jeffrey Aven
Author-email: javen@stackql.io
License: MIT
Classifier: Operating System :: Microsoft :: Windows
Classifier: Operating System :: MacOS
Classifier: Operating System :: POSIX :: Linux
Classifier: Programming Language :: Python :: 3.7
Classifier: Programming Language :: Python :: 3.8
Classifier: Programming Language :: Python :: 3.9
Classifier: Programming Language :: Python :: 3.10
Classifier: Programming Language :: Python :: 3.11
Classifier: Programming Language :: Python :: 3.12
Classifier: Programming Language :: Python :: 3.13
License-File: LICENSE
Requires-Dist: click
Requires-Dist: python-dotenv
Requires-Dist: jinja2
Requires-Dist: pystackql>=3.8.1
Requires-Dist: PyYAML
Dynamic: author
Dynamic: author-email
Dynamic: classifier
Dynamic: description
Dynamic: description-content-type
Dynamic: home-page
Dynamic: license
Dynamic: license-file
Dynamic: requires-dist
Dynamic: summary
